WaterMap/__init__.py
WaterMap/dwm/__init__.py
WaterMap/dwm/deepwatermap.py
WaterMap/dwm/dwm_wm.py
WaterMap/dwm/utils.py
WaterMap/test/__init__.py
WaterMap/test/test_build_detect.py
WaterMap/watnet/__init__.py
WaterMap/watnet/imgPatch.py
WaterMap/watnet/watnet_wm.py
WaterMap-1.0.1.dist-info/LICENSE.txt
WaterMap-1.0.1.dist-info/METADATA
WaterMap-1.0.1.dist-info/WHEEL
WaterMap-1.0.1.dist-info/top_level.txt
WaterMap-1.0.1.dist-info/RECORD
